CTFd_Crawler/__init__.py
CTFd_Crawler/dataclass.py
CTFd_Crawler/main.py
CTFd_Crawler/util.py
CTFd_Crawler-0.1.6.dist-info/METADATA
CTFd_Crawler-0.1.6.dist-info/WHEEL
CTFd_Crawler-0.1.6.dist-info/top_level.txt
CTFd_Crawler-0.1.6.dist-info/RECORD
