Metadata-Version: 2.1
Name: CTFd-Crawler
Version: 0.1.6
Summary: CTFd-Crawler is a tool designed to efficiently manage and download CTF challenge files.
Maintainer-email: h1ghl1kh7 <h1ghl1kh7@gmail.com>
License: MIT License
Project-URL: Repository, https://github.com/h1ghl1kh7/CTFd-Crawler
Requires-Dist: requests
Requires-Dist: tqdm
Requires-Dist: typing
Requires-Dist: dataclasses
